examples/branching-caesar-01.py
examples/branching-caesar-02.py
examples/branching-caesar-03.py
examples/branching00.py
examples/branching01.py
examples/branching02.py
examples/branching03.py
examples/branching04.py
examples/caesarHacker.py
examples/classy.py
examples/containers-00-search.py
examples/containers-01-range.py
examples/containers-02-off.py
examples/containers-03-primes.py
examples/containers-04-average.py
examples/containers-05-exp.py
examples/containers-06-trialdiv.py
examples/containers-07-outofrange.py
examples/containers-08-caesar-keygen.py
examples/containers-09-caesar-for.py
examples/else_01.py
examples/else_02.py
examples/else_03.py
examples/else_04.py
examples/else_05.py
examples/else_06.py
examples/fib.py
examples/functions-15-sqrt.py
examples/functions-16-caesar.py
examples/havacookie.py
examples/inline-func-calls-01.py
examples/inline-func-calls-02.py
examples/inline-func-calls-03.py
examples/inline-lambda-01.py
examples/inline-ternary-01.py
examples/lambda.py
examples/loops-00-while_pos.py
examples/loops-01-squared.py
examples/loops-02-for-each.py
examples/loops-03-range.py
examples/loops-04-exponents.py
examples/loops-05-trial-division.py
examples/loops-06-binary-down.py
examples/loops-07-binary-up.py
examples/loops-08-caesar-keygen.py
examples/loops-09-caesar-for.py
examples/loops-10-caesar-while.py
examples/racer.py
examples/sonar_improved.py
examples/speed_sort.py
examples/sudoku.py
examples/super.py
examples/switch_case.py
examples/tictactoe.py
py2cfg/__init__.py
py2cfg/_debug_hooks.py
py2cfg/_runner.py
py2cfg/_serve.py
py2cfg/_source_db.py
py2cfg/builder.py
py2cfg/model.py
py2cfg/_proto_/__init__.py
py2cfg/_proto_/src/__init__.py
py2cfg/server/__init__.py
py2cfg/server/__main__.py
py2cfg/server/_runner.py
py2cfg/server/db.py
py2cfg/server/filewatcher.py
py2cfg/server/util.py
tests/test_model.py
py2cfg-1.0.5.dist-info/LICENSE
py2cfg-1.0.5.dist-info/METADATA
py2cfg-1.0.5.dist-info/WHEEL
py2cfg-1.0.5.dist-info/entry_points.txt
py2cfg-1.0.5.dist-info/top_level.txt
py2cfg-1.0.5.dist-info/RECORD
